{"name":"常用命令","slug":"常用命令","count":1,"postlist":[{"title":"Hexo常用命令行","uid":"54054c8771f81558e75a10064f187c10","slug":"hexo/004-hexo-cmd","date":"2022-01-21T08:53:55.000Z","updated":"2022-01-26T11:03:12.143Z","comments":true,"path":"api/articles/hexo/004-hexo-cmd.json","keywords":null,"cover":"https://images.pexels.com/photos/2909083/pexels-photo-2909083.jpeg?auto=compress&cs=tinysrgb&dpr=2&h=750&w=1260","text":"本文讲述一下hexo的常用命令，相对比较简单。 1、创建博客hexo new 'my-first-blog' 2、生成静态资源文件hexo generate 或者 hexo g 3、部署到本地hexo server 或者 hexo s 4、部署到远端hexo deploy 或者 ...","link":"","photos":[],"count_time":{"symbolsCount":301,"symbolsTime":"1 mins."},"categories":[{"name":"Hexo","slug":"Hexo","count":6,"path":"api/categories/Hexo.json"}],"tags":[{"name":"Hexo","slug":"Hexo","count":5,"path":"api/tags/Hexo.json"},{"name":"常用命令","slug":"常用命令","count":1,"path":"api/tags/常用命令.json"}],"author":{"name":"ilobos","slug":"blog-author","avatar":"https://img-blog.csdnimg.cn/20210313122054101.png","link":"/","description":"","socials":{"github":"https://github.com/ilobos/","twitter":"","stackoverflow":"","wechat":"","qq":"","weibo":"","zhihu":"","csdn":"","juejin":"","customs":{"gitee":{"icon":"/svg/gitee.svg","link":"https://gitee.com/ilobos/"}}}}}]}